How2jJavaKuangjiaJiaocheng/README.md
How2jJavaKuangjiaJiaocheng/__init__.py
How2jJavaKuangjiaJiaocheng/__main__.py
How2jJavaKuangjiaJiaocheng/file.epub
How2jJavaKuangjiaJiaocheng/index.html
How2jJavaKuangjiaJiaocheng/css/__init__.py
How2jJavaKuangjiaJiaocheng/css/annotations.css
How2jJavaKuangjiaJiaocheng/css/main.css
How2jJavaKuangjiaJiaocheng/css/normalize.css
How2jJavaKuangjiaJiaocheng/css/popup.css
How2jJavaKuangjiaJiaocheng/font/__init__.py
How2jJavaKuangjiaJiaocheng/font/fontello.eot
How2jJavaKuangjiaJiaocheng/font/fontello.svg
How2jJavaKuangjiaJiaocheng/font/fontello.ttf
How2jJavaKuangjiaJiaocheng/font/fontello.woff
How2jJavaKuangjiaJiaocheng/img/__init__.py
How2jJavaKuangjiaJiaocheng/img/annotator-glyph-sprite.png
How2jJavaKuangjiaJiaocheng/img/annotator-icon-sprite.png
How2jJavaKuangjiaJiaocheng/img/apple-touch-icon.png
How2jJavaKuangjiaJiaocheng/img/cancelfullscreen.png
How2jJavaKuangjiaJiaocheng/img/close.png
How2jJavaKuangjiaJiaocheng/img/fullscreen.png
How2jJavaKuangjiaJiaocheng/img/loader.gif
How2jJavaKuangjiaJiaocheng/img/menu-icon.png
How2jJavaKuangjiaJiaocheng/img/save.png
How2jJavaKuangjiaJiaocheng/img/saved.png
How2jJavaKuangjiaJiaocheng/img/settings-s.png
How2jJavaKuangjiaJiaocheng/img/settings.png
How2jJavaKuangjiaJiaocheng/img/star.png
How2jJavaKuangjiaJiaocheng/js/__init__.py
How2jJavaKuangjiaJiaocheng/js/epub.js
How2jJavaKuangjiaJiaocheng/js/epub.min.js
How2jJavaKuangjiaJiaocheng/js/epub.min.map
How2jJavaKuangjiaJiaocheng/js/hooks.min.js
How2jJavaKuangjiaJiaocheng/js/hooks.min.map
How2jJavaKuangjiaJiaocheng/js/reader.js
How2jJavaKuangjiaJiaocheng/js/reader.js.map
How2jJavaKuangjiaJiaocheng/js/reader.min.js
How2jJavaKuangjiaJiaocheng/js/reader.min.map
How2jJavaKuangjiaJiaocheng/js/hooks/__init__.py
How2jJavaKuangjiaJiaocheng/js/hooks/extensions/__init__.py
How2jJavaKuangjiaJiaocheng/js/hooks/extensions/highlight.js
How2jJavaKuangjiaJiaocheng/js/libs/__init__.py
How2jJavaKuangjiaJiaocheng/js/libs/jquery.min.js
how2j_java_kuangjia_jiaocheng-2024.3.5.0.dist-info/METADATA
how2j_java_kuangjia_jiaocheng-2024.3.5.0.dist-info/WHEEL
how2j_java_kuangjia_jiaocheng-2024.3.5.0.dist-info/entry_points.txt
how2j_java_kuangjia_jiaocheng-2024.3.5.0.dist-info/top_level.txt
how2j_java_kuangjia_jiaocheng-2024.3.5.0.dist-info/RECORD
